geometry_msgs/_dummy.cpython-310-x86_64-linux-gnu.so
ros_geometry_msgs-5.5.1.data/data/include/geometry_msgs/geometry_msgs/msg/accel.h
ros_geometry_msgs-5.5.1.data/data/include/geometry_msgs/geometry_msgs/msg/accel.hpp
ros_geometry_msgs-5.5.1.data/data/include/geometry_msgs/geometry_msgs/msg/accel_stamped.h
ros_geometry_msgs-5.5.1.data/data/include/geometry_msgs/geometry_msgs/msg/accel_stamped.hpp
ros_geometry_msgs-5.5.1.data/data/include/geometry_msgs/geometry_msgs/msg/accel_with_covariance.h
ros_geometry_msgs-5.5.1.data/data/include/geometry_msgs/geometry_msgs/msg/accel_with_covariance.hpp
ros_geometry_msgs-5.5.1.data/data/include/geometry_msgs/geometry_msgs/msg/accel_with_covariance_stamped.h
ros_geometry_msgs-5.5.1.data/data/include/geometry_msgs/geometry_msgs/msg/accel_with_covariance_stamped.hpp
ros_geometry_msgs-5.5.1.data/data/include/geometry_msgs/geometry_msgs/msg/inertia.h
ros_geometry_msgs-5.5.1.data/data/include/geometry_msgs/geometry_msgs/msg/inertia.hpp
ros_geometry_msgs-5.5.1.data/data/include/geometry_msgs/geometry_msgs/msg/inertia_stamped.h
ros_geometry_msgs-5.5.1.data/data/include/geometry_msgs/geometry_msgs/msg/inertia_stamped.hpp
ros_geometry_msgs-5.5.1.data/data/include/geometry_msgs/geometry_msgs/msg/point.h
ros_geometry_msgs-5.5.1.data/data/include/geometry_msgs/geometry_msgs/msg/point.hpp
ros_geometry_msgs-5.5.1.data/data/include/geometry_msgs/geometry_msgs/msg/point32.h
ros_geometry_msgs-5.5.1.data/data/include/geometry_msgs/geometry_msgs/msg/point32.hpp
ros_geometry_msgs-5.5.1.data/data/include/geometry_msgs/geometry_msgs/msg/point_stamped.h
ros_geometry_msgs-5.5.1.data/data/include/geometry_msgs/geometry_msgs/msg/point_stamped.hpp
ros_geometry_msgs-5.5.1.data/data/include/geometry_msgs/geometry_msgs/msg/polygon.h
ros_geometry_msgs-5.5.1.data/data/include/geometry_msgs/geometry_msgs/msg/polygon.hpp
ros_geometry_msgs-5.5.1.data/data/include/geometry_msgs/geometry_msgs/msg/polygon_instance.h
ros_geometry_msgs-5.5.1.data/data/lib/python3.10/site-packages/geometry_msgs-5.5.1-py3.10.egg-info/PKG-INFO
ros_geometry_msgs-5.5.1.data/data/lib/python3.10/site-packages/geometry_msgs-5.5.1-py3.10.egg-info/SOURCES.txt
ros_geometry_msgs-5.5.1.data/data/lib/python3.10/site-packages/geometry_msgs-5.5.1-py3.10.egg-info/dependency_links.txt
ros_geometry_msgs-5.5.1.data/data/lib/python3.10/site-packages/geometry_msgs-5.5.1-py3.10.egg-info/top_level.txt
ros_geometry_msgs-5.5.1.dist-info/METADATA
ros_geometry_msgs-5.5.1.dist-info/WHEEL
ros_geometry_msgs-5.5.1.dist-info/top_level.txt
ros_geometry_msgs-5.5.1.dist-info/RECORD
ros_geometry_msgs-5.5.1.dist-info/licenses/LICENSE
