Metadata-Version: 2.4
Name: ros-geometry-msgs
Version: 5.5.1
Summary: ROS geometry_msgs provides data types for common geometric primitives like points, vectors, poses, acceleration, and inertia, facilitating system interoperability.
License-File: LICENSE
Requires-Dist: ros-rosidl-default-runtime~=1.7.1
Requires-Dist: ros-std-msgs~=5.5.1
Dynamic: description
Dynamic: description-content-type
Dynamic: license-file
Dynamic: requires-dist
Dynamic: summary
